swiftcrawl/__init__.py
swiftcrawl/browser_client.py
swiftcrawl/cli.py
swiftcrawl/core.py
swiftcrawl/crawler.py
swiftcrawl/downloader.py
swiftcrawl/http_client.py
swiftcrawl/items.py
swiftcrawl/py.typed
swiftcrawl/request.py
swiftcrawl/response.py
swiftcrawl/scheduler.py
swiftcrawl/settings.py
swiftcrawl/spider.py
swiftcrawl-0.1.3.dist-info/WHEEL
swiftcrawl-0.1.3.dist-info/entry_points.txt
swiftcrawl-0.1.3.dist-info/METADATA
swiftcrawl-0.1.3.dist-info/RECORD
