Metadata-Version: 2.3
Name: swiftcrawl
Version: 0.1.3
Summary: A powerful, flexible web scraping abstraction layer that seamlessly handles both lightweight HTTP requests and full browser automation with anti-detection capabilities
Author: MaxiLR
Author-email: MaxiLR <maximolr.itr@gmail.com>
Requires-Dist: beautifulsoup4>=4.14.2
Requires-Dist: browserforge>=1.2.3
Requires-Dist: camoufox>=0.4.11
Requires-Dist: httpx>=0.28.1
Requires-Dist: lxml>=6.0.2
Requires-Dist: playwright>=1.56.0
Requires-Python: >=3.12
